roundup/__init__.py
roundup/roundup.py
roundup_csv-1.1.1.dist-info/LICENSE
roundup_csv-1.1.1.dist-info/METADATA
roundup_csv-1.1.1.dist-info/WHEEL
roundup_csv-1.1.1.dist-info/entry_points.txt
roundup_csv-1.1.1.dist-info/top_level.txt
roundup_csv-1.1.1.dist-info/RECORD
