Metadata-Version: 2.1
Name: roundup-csv
Version: 1.1.1
Summary: Rounds up transactions in CSV file
Home-page: https://github.com/reedhaffner/CSV-RoundUps
Author: Reed Haffner
Author-email: reedhaffner@pm.me
License: GPL 3.0
Platform: UNKNOWN
Classifier: Development Status :: 4 - Beta
Classifier: Environment :: Console
Classifier: License :: OSI Approved :: GNU General Public License v3 (GPLv3)
Classifier: Natural Language :: English
Classifier: Operating System :: OS Independent
Classifier: Programming Language :: Python :: 3.7
Classifier: Topic :: Office/Business :: Financial
Classifier: Topic :: Office/Business :: Financial :: Spreadsheet
